{
  "$schema": "http://json-schema.org/schema#",
  "properties": {
    "result_parameters": {
      "properties": {
        "attribution_source": {
          "type": "string"
        },
        "attribution_type": {
          "type": "string"
        },
        "end_date": {
          "type": "string"
        },
        "events": {
          "items": {
            "properties": {
              "name": {
                "type": "string"
              },
              "token": {
                "type": "string"
              }
            },
            "type": "object"
          },
          "type": "array"
        },
        "grouping": {
          "items": {
            "type": "string"
          },
          "type": "array"
        },
        "kpis": {
          "items": {
            "type": "string"
          },
          "type": "array"
        },
        "sandbox": {
          "type": "boolean"
        },
        "start_date": {
          "type": "string"
        },
        "trackers": {
          "items": {
            "properties": {
              "has_subtrackers": {
                "type": "boolean"
              },
              "name": {
                "type": "string"
              },
              "token": {
                "type": "string"
              }
            },
            "type": "object"
          },
          "type": "array"
        },
        "utc_offset": {
          "type": "string"
        }
      },
      "type": "object"
    },
    "result_set": {
      "properties": {
        "currency": {
          "type": "string"
        },
        "name": {
          "type": "string"
        },
        "token": {
          "type": "string"
        },
        "trackers": {
          "items": {
            "properties": {
              "countries": {
                "items": {
                  "properties": {
                    "country": {
                      "type": "string"
                    },
                    "kpi_values": {
                      "items": {
                        "type": "number"
                      },
                      "type": "array"
                    }
                  },
                  "type": "object"
                },
                "type": "array"
              },
              "token": {
                "type": "string"
              }
            },
            "type": "object"
          },
          "type": "array"
        }
      },
      "type": "object"
    }
  },
  "type": "object"
}